flywheel_metadata/__init__.py
flywheel_metadata/file/__init__.py
flywheel_metadata/file/dicom/__init__.py
flywheel_metadata/file/dicom/dictionaries.py
flywheel_metadata/file/dicom/fixer.py
flywheel_metadata/file/dicom/tracker.py
flywheel_metadata_toolkit-0.1.4.dist-info/METADATA
flywheel_metadata_toolkit-0.1.4.dist-info/WHEEL
flywheel_metadata_toolkit-0.1.4.dist-info/top_level.txt
flywheel_metadata_toolkit-0.1.4.dist-info/RECORD
