Metadata-Version: 2.1
Name: flywheel-metadata-toolkit
Version: 0.1.4
Summary: Flywheel Metadata Toolkit
Home-page: UNKNOWN
Author-email: support@flywheel.io
License: MIT
Project-URL: Source, https://gitlab.com/flywheel-io/public/metadata-toolkit
Keywords: Flywheel,flywheel,data,metadata,toolkit
Platform: UNKNOWN
Requires-Dist: fs (~=2.4.0)
Requires-Dist: pydicom (~=2.1.0)
Provides-Extra: dev
Requires-Dist: black (==20.8b1) ; extra == 'dev'
Requires-Dist: pytest (~=5.1.0) ; extra == 'dev'
Requires-Dist: pytest-cov (~=2.7.0) ; extra == 'dev'
